boc_hosts/__init__.py
boc_hosts/hosts.py
boc_hosts-0.0.2.dist-info/LICENSE
boc_hosts-0.0.2.dist-info/METADATA
boc_hosts-0.0.2.dist-info/WHEEL
boc_hosts-0.0.2.dist-info/top_level.txt
boc_hosts-0.0.2.dist-info/RECORD
