Metadata-Version: 2.1
Name: boc-hosts
Version: 0.0.2
Summary: A tool to manage the hosts file
Home-page: https://github.com/bitofcode/py-boc-hosts
Author: Wassim Akachi
Author-email: wassim@bitofcode.com
License: UNKNOWN
Platform: UNKNOWN
Classifier: Programming Language :: Python :: 3
Classifier: License :: OSI Approved :: MIT License
Classifier: Operating System :: OS Independent
Requires-Python: >=3.6
